smcryptopy-0.2.1.dist-info/METADATA
smcryptopy-0.2.1.dist-info/WHEEL
smcryptopy/sm2.py
smcryptopy/sm3.py
smcryptopy/sm4.py
smcryptopy/tests/test_sm2.py
smcryptopy/tests/test_sm3.py
smcryptopy/tests/test_sm4.py
smcryptopy/tests/__init__.py
smcryptopy/_exceptions.py
smcryptopy/__init__.py
smcryptopy/_smcryptopy/__init__.py
smcryptopy/_smcryptopy/ffi.py
smcryptopy/_smcryptopy/native.so
smcryptopy-0.2.1.dist-info/RECORD
