Metadata-Version: 2.1
Name: smcryptopy
Version: 0.2.1
Classifier: Programming Language :: Rust
Classifier: Programming Language :: Python :: Implementation :: CPython
Classifier: Programming Language :: Python :: Implementation :: PyPy
Requires-Dist: cffi
Summary: A Rust Implementation of China's Standards of Encryption Algorithms(SM2/SM3/SM4)
Keywords: cipher,cryptography
Author: yumeng <yumeng@foxmail.com>
Author-email: yumeng <yumeng@foxmail.com>
License: MIT
Requires-Python: >=3.8
Project-URL: Source Code, https://github.com/zhuobie/smcrypto-ffi
